atp/__init__.py
atp/setup.py
atp/types.py
atp/core/__init__.py
atp/core/atp_envelope.py
atp/examples/__init__.py
atp/examples/async_demo.py
atp/examples/holistic_demo.py
atp/examples/http_transport_demo.py
atp/examples/policy_demo.py
atp/examples/simple_http_demo.py
atp/policy/__init__.py
atp/policy/policy_engine.py
atp/policy/policy_manager.py
atp/protocol/__init__.py
atp/protocol/atp_client.py
atp/registry/__init__.py
atp/registry/agent_registry.py
atp/transport/__init__.py
atp/transport/base_transport.py
atp/transport/grpc_transport.py
atp/transport/http_transport.py
atp/transport/in_memory_transport.py
atp/transport/kafka_transport.py
atp/transport/mqtt_transport.py
atp/transport/websocket_transport.py
agent_trust_protocol-1.1.1.dist-info/METADATA
agent_trust_protocol-1.1.1.dist-info/WHEEL
agent_trust_protocol-1.1.1.dist-info/entry_points.txt
agent_trust_protocol-1.1.1.dist-info/top_level.txt
agent_trust_protocol-1.1.1.dist-info/RECORD
