Metadata-Version: 2.4
Name: agent-trust-protocol
Version: 1.1.1
Summary: A comprehensive security and provenance framework for secure, trustworthy communication between autonomous AI agents, IoT devices, microservices, and any system requiring cryptographic trust
Home-page: https://github.com/agent-trust-protocol/agent-trust-protocol
Author: Agent Trust Protocol Team
Author-email: team@agent-trust-protocol.org
Project-URL: Bug Reports, https://github.com/agent-trust-protocol/agent-trust-protocol/issues
Project-URL: Source, https://github.com/agent-trust-protocol/agent-trust-protocol
Project-URL: Documentation, https://github.com/agent-trust-protocol/agent-trust-protocol/docs
Keywords: agent,trust,protocol,security,cryptography,async,communication,autonomous,ai,distributed
Classifier: Development Status :: 4 - Beta
Classifier: Intended Audience :: Developers
Classifier: License :: OSI Approved :: MIT License
Classifier: Operating System :: OS Independent
Classifier: Programming Language :: Python :: 3
Classifier: Programming Language :: Python :: 3.8
Classifier: Programming Language :: Python :: 3.9
Classifier: Programming Language :: Python :: 3.10
Classifier: Programming Language :: Python :: 3.11
Classifier: Programming Language :: Python :: 3.12
Classifier: Topic :: Security
Classifier: Topic :: Software Development :: Libraries :: Python Modules
Classifier: Topic :: System :: Distributed Computing
Classifier: Topic :: Communications
Requires-Python: >=3.8
Provides-Extra: dev
Requires-Dist: pytest>=7.4.3; extra == "dev"
Requires-Dist: pytest-asyncio>=0.21.1; extra == "dev"
Requires-Dist: black>=23.11.0; extra == "dev"
Requires-Dist: flake8>=6.1.0; extra == "dev"
Requires-Dist: mypy>=1.7.1; extra == "dev"
Provides-Extra: crypto
Requires-Dist: pycryptodome>=3.19.0; extra == "crypto"
Dynamic: author
Dynamic: author-email
Dynamic: classifier
Dynamic: description
Dynamic: description-content-type
Dynamic: home-page
Dynamic: keywords
Dynamic: project-url
Dynamic: provides-extra
Dynamic: requires-python
Dynamic: summary
